COPYING
MANIFEST.in
Makefile
README.rst
pyproject.toml
setup.py
data/kickstart.vim
docs/2to3
docs/kickstart-docs.txt
docs/ksflatten.1
docs/ksshell.1
docs/ksvalidator.1
docs/ksverdiff.1
docs/programmers-guide
po/Makefile
po/ar.mo
po/ar.po
po/as.mo
po/as.po
po/ast.mo
po/ast.po
po/bg.mo
po/bg.po
po/bn.mo
po/bn.po
po/bn_IN.mo
po/bn_IN.po
po/bs.mo
po/bs.po
po/ca.mo
po/ca.po
po/cs.mo
po/cs.po
po/da.mo
po/da.po
po/de.mo
po/de.po
po/de_CH.mo
po/de_CH.po
po/el.mo
po/el.po
po/en_GB.mo
po/en_GB.po
po/es.mo
po/es.po
po/eu.mo
po/eu.po
po/fa.mo
po/fa.po
po/fi.mo
po/fi.po
po/fr.mo
po/fr.po
po/gl.mo
po/gl.po
po/gu.mo
po/gu.po
po/he.mo
po/he.po
po/hi.mo
po/hi.po
po/hr.mo
po/hr.po
po/hu.mo
po/hu.po
po/ia.mo
po/ia.po
po/id.mo
po/id.po
po/is.mo
po/is.po
po/it.mo
po/it.po
po/ja.mo
po/ja.po
po/ka.mo
po/ka.po
po/kn.mo
po/kn.po
po/ko.mo
po/ko.po
po/mai.mo
po/mai.po
po/mk.mo
po/mk.po
po/ml.mo
po/ml.po
po/mr.mo
po/mr.po
po/ms.mo
po/ms.po
po/nb.mo
po/nb.po
po/nds.mo
po/nds.po
po/nl.mo
po/nl.po
po/or.mo
po/or.po
po/pa.mo
po/pa.po
po/pl.mo
po/pl.po
po/pt.mo
po/pt.po
po/pt_BR.mo
po/pt_BR.po
po/pykickstart.pot
po/ru.mo
po/ru.po
po/si.mo
po/si.po
po/sk.mo
po/sk.po
po/sl.mo
po/sl.po
po/sr.mo
po/sr.po
po/sr@latin.mo
po/sr@latin.po
po/sv.mo
po/sv.po
po/ta.mo
po/ta.po
po/te.mo
po/te.po
po/th.mo
po/th.po
po/tr.mo
po/tr.po
po/uk.mo
po/uk.po
po/zh_CN.mo
po/zh_CN.po
po/zh_TW.mo
po/zh_TW.po
pykickstart/__init__.py
pykickstart/base.py
pykickstart/constants.py
pykickstart/errors.py
pykickstart/i18n.py
pykickstart/ko.py
pykickstart/load.py
pykickstart/options.py
pykickstart/parser.py
pykickstart/sections.py
pykickstart/version.py
pykickstart.egg-info/PKG-INFO
pykickstart.egg-info/SOURCES.txt
pykickstart.egg-info/dependency_links.txt
pykickstart.egg-info/requires.txt
pykickstart.egg-info/top_level.txt
pykickstart/commands/__init__.py
pykickstart/commands/authconfig.py
pykickstart/commands/authselect.py
pykickstart/commands/autopart.py
pykickstart/commands/autostep.py
pykickstart/commands/bootc.py
pykickstart/commands/bootloader.py
pykickstart/commands/btrfs.py
pykickstart/commands/cdrom.py
pykickstart/commands/clearpart.py
pykickstart/commands/device.py
