Metadata-Version: 2.4
Name: pykickstart
Version: 3.67
Summary: Python module for manipulating kickstart files
Home-page: https://fedoraproject.org/wiki/pykickstart
Author: Chris Lumens
Author-email: Chris Lumens <clumens@redhat.com>
Maintainer-email: "Brian C. Lane" <bcl@redhat.com>
Project-URL: Homepage, https://fedoraproject.org/wiki/pykickstart
Project-URL: Bug Tracker, https://github.com/pykickstart/pykickstart/issues
Classifier: Programming Language :: Python :: 3
Classifier: License :: OSI Approved :: GNU General Public License (GPL)
Classifier: Operating System :: OS Independent
Requires-Python: >=3.6
License-File: COPYING
Requires-Dist: requests
Dynamic: author
Dynamic: home-page
Dynamic: license-file
Dynamic: requires-dist
